docs/source/conf.py
src/Oublie/__init__.py
src/Oublie/example.py
src/Oublie/huatu.py
oublie_python-1.1.0.dist-info/METADATA
oublie_python-1.1.0.dist-info/WHEEL
oublie_python-1.1.0.dist-info/licenses/LICENSE
oublie_python-1.1.0.dist-info/RECORD
