Metadata-Version: 2.1
Name: Oublie-Python
Version: 1.1.0
Summary: Oublie的个人Python模块
Project-URL: Homepage, https://github.com/oublie6/Oublie-Python
Project-URL: Bug Tracker, https://github.com/oublie6/Oublie-Python/issues
Author-email: Oublie <313166062@qq.com>
License-File: LICENSE
Classifier: License :: OSI Approved :: MIT License
Classifier: Operating System :: OS Independent
Classifier: Programming Language :: Python :: 3
Requires-Python: >=3.7
Requires-Dist: matplotlib
Requires-Dist: networkx
